wavify/__init__.py
wavify/stt.py
wavify/types.py
wavify/utils.py
wavify/wakeword.py
wavify/lib/aarch64-apple-darwin/libtensorflowlite_c.dylib
wavify/lib/aarch64-apple-darwin/libwavify_core.dylib
wavify/lib/aarch64-unknown-linux-gnu/libtensorflowlite_c.so
wavify/lib/aarch64-unknown-linux-gnu/libwavify_core.so
wavify/lib/x86_64-pc-windows-gnu/tensorflowlite_c.dll
wavify/lib/x86_64-pc-windows-gnu/wavify_core.dll
wavify/lib/x86_64-unknown-linux-gnu/libtensorflowlite_c.so
wavify/lib/x86_64-unknown-linux-gnu/libwavify_core.so
wavify-0.0.18.dist-info/METADATA
wavify-0.0.18.dist-info/WHEEL
wavify-0.0.18.dist-info/licenses/LICENSE
wavify-0.0.18.dist-info/RECORD
