Metadata-Version: 2.4
Name: wavify
Version: 0.0.18
Summary: Wavify Python SDK
Project-URL: Homepage, https://wavify.dev
Project-URL: Issues, https://github.com/wavify-labs/wavify-sdks/issues
Author-email: Manuel Plank <manuel@wavify.dev>
License:                                  Apache License
License-File: LICENSE
Keywords: ASR,Automatic Speech Recognition,STT,Speech Recognition,Speech-to-Text,Voice Recognition,Wake word
Classifier: Operating System :: OS Independent
Classifier: Programming Language :: Python :: 3
Requires-Python: >=3.8
